solpyb/__init__.py
solpyb/base.py
solpyb/connectivity.py
solpyb/wallet.py
solpyb-0.0.2.dist-info/LICENSE
solpyb-0.0.2.dist-info/WHEEL
solpyb-0.0.2.dist-info/METADATA
solpyb-0.0.2.dist-info/RECORD
