Metadata-Version: 2.1
Name: solpyb
Version: 0.0.2
Summary: Pythonic Bridge to Solana Programs
License: LGPL2.1
Author: amor71
Author-email: amor71@sgeltd.com
Requires-Python: >=3.10,<4.0
Classifier: License :: Other/Proprietary License
Classifier: Programming Language :: Python :: 3
Classifier: Programming Language :: Python :: 3.10
Requires-Dist: solana (>=0.25.1,<0.26.0)
